NS-MapToolkit/NSMapToolkit.py
NS-MapToolkit/__init__.py
NS-MapToolkit/modelSystems.py
NSMap/NSMapToolkit.py
NSMap/__init__.py
NSMap/modelSystems.py
NSMap-1.0.dist-info/LICENSE
NSMap-1.0.dist-info/METADATA
NSMap-1.0.dist-info/WHEEL
NSMap-1.0.dist-info/top_level.txt
NSMap-1.0.dist-info/RECORD
